{"cameraMode":{"drawMode":0,"name":"Shaded","section":"Shading Mode"},"sceneLighting":false,"audioPlay":false,"sceneViewState":{"m_AlwaysRefresh":false,"showFog":true,"showSkybox":false,"showFlares":true,"showImageEffects":true,"showParticleSystems":true,"showVisualEffectGraphs":true,"m_FxEnabled":true},"in2DMode":false,"pivot":{"x":4.38494873046875,"y":0.9839733242988586,"z":6.325038433074951},"rotation":{"x":0.03743326663970947,"y":0.27950534224510195,"z":-0.010906947776675225,"w":0.959354817867279},"size":7.029723167419434,"orthographic":false}